eBonsParser/__init__.py
eBonsParser/stores.py
eBonsParser/utils.py
eBonsParser/models/__init__.py
eBonsParser/models/base.py
eBonsParser/models/item.py
eBonsParser/models/payment.py
eBonsParser/models/receipt.py
ebonsparser-0.1.1.dist-info/licenses/LICENSE
ebonsparser-0.1.1.dist-info/METADATA
ebonsparser-0.1.1.dist-info/WHEEL
ebonsparser-0.1.1.dist-info/top_level.txt
ebonsparser-0.1.1.dist-info/RECORD
