Metadata-Version: 2.4
Name: eBonsParser
Version: 0.1.1
Summary: A Python library to parse German eBon (digital receipt) PDFs. Currently supports REWE/Thalia receipts.
Author-email: Oussama Raies <oussama.raies@rwth-aachen.de>
License: MIT
Requires-Python: >=3.10
License-File: LICENSE
Requires-Dist: pydantic>=2.0
Requires-Dist: pdfplumber
Provides-Extra: dev
Requires-Dist: pytest; extra == "dev"
Requires-Dist: black; extra == "dev"
Requires-Dist: mypy; extra == "dev"
Dynamic: license-file
